Metadata-Version: 2.1
Name: oneNeuron-pypi-Pavan164-ml
Version: 0.0.3
Summary: its an implimentation of Perceptron
Home-page: https://github.com/Pavan164-ml/oneNeuron_pypi
Author: Pavan164-ml
Author-email: pavanram2000@gmail.com
License: UNKNOWN
Project-URL: Bug Tracker, https://github.com/Pavan164-ml/oneNeuron_pypi/issues
Platform: UNKNOWN
Classifier: Programming Language :: Python :: 3
Classifier: License :: OSI Approved :: MIT License
Classifier: Operating System :: OS Independent
Requires-Python: >=3.7
License-File: LICENSE
Requires-Dist: numpy
Requires-Dist: tqdm
